{
  "name": "mkultra:necrotide_golem",
  "slotItems": {
    "mkweapons:hands": [
      {
        "template": {
          "lootSlot": "mkweapons:hands",
          "options": [
            {
              "type": "mkweapons:accessory_effect",
              "effects": [
                {
                  "type": "mkweapons:accessory_effect.on_hit_ability",
                  "value": {
                    "ability": "mkultra:engulfing_darkness",
                    "proc_chance": {
                      "max": 0.15,
                      "min": 0.05
                    },
                    "skill_level": {
                      "max": 100.0,
                      "min": 0.0
                    }
                  }
                }
              ]
            },
            {
              "type": "mkweapons:attributes",
              "modifiers": [
                {
                  "attribute": "minecraft:generic.max_health",
                  "maxValue": 30.0,
                  "minValue": 6.0,
                  "modifier": {
                    "amount": 6.0,
                    "name": "mkultra:necrotide_golem",
                    "operation": 0
                  }
                }
              ]
            },
            {
              "type": "mkweapons:attributes",
              "modifiers": [
                {
                  "attribute": "mkcore:max_mana",
                  "maxValue": 30.0,
                  "minValue": 6.0,
                  "modifier": {
                    "amount": 6.0,
                    "name": "mkultra:necrotide_golem",
                    "operation": 0
                  }
                }
              ]
            },
            {
              "type": "mkweapons:attributes",
              "modifiers": [
                {
                  "attribute": "mkcore:mana_regen",
                  "maxValue": 4.0,
                  "minValue": 0.5,
                  "modifier": {
                    "amount": 0.5,
                    "name": "mkultra:necrotide_golem",
                    "operation": 0
                  }
                }
              ]
            },
            {
              "type": "mkweapons:attributes",
              "modifiers": [
                {
                  "attribute": "mkcore:necromancy",
                  "maxValue": 10.0,
                  "minValue": 2.0,
                  "modifier": {
                    "amount": 2.0,
                    "name": "mkultra:necrotide_golem",
                    "operation": 0
                  }
                }
              ]
            },
            {
              "type": "mkweapons:attributes",
              "modifiers": [
                {
                  "attribute": "mkcore:shadow_damage",
                  "maxValue": 8.0,
                  "minValue": 2.0,
                  "modifier": {
                    "amount": 2.0,
                    "name": "mkultra:necrotide_golem",
                    "operation": 0
                  }
                }
              ]
            },
            {
              "type": "mkweapons:attributes",
              "modifiers": [
                {
                  "attribute": "mkcore:shadow_resistance",
                  "maxValue": 0.2,
                  "minValue": 0.05,
                  "modifier": {
                    "amount": 0.05,
                    "name": "mkultra:necrotide_golem",
                    "operation": 0
                  }
                }
              ]
            }
          ],
          "potentialItems": [
            {
              "item": {
                "Count": 1,
                "id": "mkultra:corrupted_gauntlets"
              }
            },
            {
              "item": {
                "Count": 1,
                "id": "mkultra:necrotide_band"
              }
            }
          ],
          "templates": [
            {
              "template": {
                "name": "mkultra:corrupted_gauntlets_crit",
                "slots": [
                  "mkweapons:randomization.effect",
                  "mkweapons:randomization.attributes",
                  "mkweapons:randomization.attributes"
                ]
              }
            },
            {
              "template": {
                "name": "mkultra:corrupted_gauntlets",
                "slots": [
                  "mkweapons:randomization.effect",
                  "mkweapons:randomization.attributes"
                ]
              },
              "weight": 10.0
            }
          ]
        },
        "weight": 10.0
      }
    ],
    "mkweapons:rings": [
      {
        "template": {
          "lootSlot": "mkweapons:rings",
          "options": [
            {
              "type": "mkweapons:accessory_effect",
              "effects": [
                {
                  "type": "mkweapons:accessory_effect.restore_mana",
                  "chance": {
                    "max": 0.25,
                    "min": 0.05
                  },
                  "percentage": {
                    "max": 1.0,
                    "min": 0.1
                  }
                }
              ]
            },
            {
              "type": "mkweapons:attributes",
              "modifiers": [
                {
                  "attribute": "minecraft:generic.max_health",
                  "maxValue": 30.0,
                  "minValue": 6.0,
                  "modifier": {
                    "amount": 6.0,
                    "name": "mkultra:necrotide_golem",
                    "operation": 0
                  }
                }
              ]
            },
            {
              "type": "mkweapons:attributes",
              "modifiers": [
                {
                  "attribute": "mkcore:max_mana",
                  "maxValue": 30.0,
                  "minValue": 6.0,
                  "modifier": {
                    "amount": 6.0,
                    "name": "mkultra:necrotide_golem",
                    "operation": 0
                  }
                }
              ]
            },
            {
              "type": "mkweapons:attributes",
              "modifiers": [
                {
                  "attribute": "mkcore:mana_regen",
                  "maxValue": 4.0,
                  "minValue": 0.5,
                  "modifier": {
                    "amount": 0.5,
                    "name": "mkultra:necrotide_golem",
                    "operation": 0
                  }
                }
              ]
            },
            {
              "type": "mkweapons:attributes",
              "modifiers": [
                {
                  "attribute": "mkcore:necromancy",
                  "maxValue": 10.0,
                  "minValue": 2.0,
                  "modifier": {
                    "amount": 2.0,
                    "name": "mkultra:necrotide_golem",
                    "operation": 0
                  }
                }
              ]
            },
            {
              "type": "mkweapons:attributes",
              "modifiers": [
                {
                  "attribute": "mkcore:shadow_damage",
                  "maxValue": 8.0,
                  "minValue": 2.0,
                  "modifier": {
                    "amount": 2.0,
                    "name": "mkultra:necrotide_golem",
                    "operation": 0
                  }
                }
              ]
            },
            {
              "type": "mkweapons:attributes",
              "modifiers": [
                {
                  "attribute": "mkcore:shadow_resistance",
                  "maxValue": 0.2,
                  "minValue": 0.05,
                  "modifier": {
                    "amount": 0.05,
                    "name": "mkultra:necrotide_golem",
                    "operation": 0
                  }
                }
              ]
            }
          ],
          "potentialItems": [],
          "templates": [
            {
              "template": {
                "name": "mkultra:necrotide_band_crit",
                "slots": [
                  "mkweapons:randomization.effect",
                  "mkweapons:randomization.attributes",
                  "mkweapons:randomization.attributes"
                ]
              }
            },
            {
              "template": {
                "name": "mkultra:necrotide_band",
                "slots": [
                  "mkweapons:randomization.effect",
                  "mkweapons:randomization.attributes"
                ]
              },
              "weight": 10.0
            }
          ]
        },
        "weight": 20.0
      }
    ]
  }
}